<Comics>
	<panel name="panel00000">
		<filename str="img/00000.png"></filename>
		<position x="0" y="0"></position>
		<vel value="5"></vel>
		<root enabled="true"></root>
		<blank enabled="false"></blank>
		<dirs>
			<up nextComic="null"></up>
			<down nextComic="null"></down>
			<left nextComic="null"></left>
			<right nextComic="panel00001"></right>
		</dirs>
	</panel>
	<panel name="panel00001" autopos="true">
		<filename str="img/00002.png"></filename>
		<position x="553" y="50"></position>
		<vel value="5"></vel>		
		<root enabled="false"></root>
		<blank enabled="false"></blank>
		<dirs>
			<up nextComic="null"></up>
			<down nextComic="null"></down>
			<left nextComic="panel00000"></left>
			<right nextComic="panel00002"></right>
		</dirs>
	</panel>
	<panel name="panel00002">
		<filename str="sample.bmp"></filename>
		<position x="1206" y="256"></position>
		<vel value="5"></vel>		
		<root enabled="false"></root>
		<blank enabled="false"></blank>
		<dirs>
			<up nextComic="null"></up>
			<down nextComic="null"></down>
			<left nextComic="panel00001"></left>
			<right nextComic="panel00003"></right>
		</dirs>
	</panel>
	<panel name="panel00003" autopos="true">
		<filename str="img/00004.png"></filename>
		<position x="2006" y="0"></position>
		<vel value="5"></vel>		
		<root enabled="false"></root>
		<blank enabled="false"></blank>
		<dirs>
			<up nextComic="null"></up>
			<down nextComic="null"></down>
			<left nextComic="panel00002"></left>
			<right nextComic="null"></right>
		</dirs>
	</panel>
</Comics>
